odoo9_addon_privacy_partner_report-9.0.1.0.0.99.dev2-py2.7-nspkg.pth
odoo9_addon_privacy_partner_report-9.0.1.0.0.99.dev2.dist-info/METADATA
odoo9_addon_privacy_partner_report-9.0.1.0.0.99.dev2.dist-info/RECORD
odoo9_addon_privacy_partner_report-9.0.1.0.0.99.dev2.dist-info/WHEEL
odoo9_addon_privacy_partner_report-9.0.1.0.0.99.dev2.dist-info/namespace_packages.txt
odoo9_addon_privacy_partner_report-9.0.1.0.0.99.dev2.dist-info/top_level.txt
odoo_addons/privacy_partner_report/README.rst
odoo_addons/privacy_partner_report/__init__.py
odoo_addons/privacy_partner_report/__openerp__.py
odoo_addons/privacy_partner_report/controllers/__init__.py
odoo_addons/privacy_partner_report/controllers/main.py
odoo_addons/privacy_partner_report/i18n/fr.po
odoo_addons/privacy_partner_report/i18n/privacy_partner_report.pot
odoo_addons/privacy_partner_report/report/__init__.py
odoo_addons/privacy_partner_report/report/privacy_partner_xlsx.py
odoo_addons/privacy_partner_report/static/description/icon.png
odoo_addons/privacy_partner_report/views/privacy_menu_view.xml
odoo_addons/privacy_partner_report/views/privacy_report.xml
odoo_addons/privacy_partner_report/wizard/__init__.py
odoo_addons/privacy_partner_report/wizard/privacy_report_partner.py
odoo_addons/privacy_partner_report/wizard/privacy_report_partner_wizard.xml
